[
    {
        "name": "Student 1 Name",
        "surname": "Student 1 Surname",
        "github": "http://github.com/student1",
        "email": "student1@gmail.com"
    }, {
        "name": "Student 1 Name",
        "surname": "Student 1 Surname",
        "github": "http://github.com/student1",
        "email": "student1@gmail.com"
    }, {
        "name": "Student 1 Name",
        "surname": "Student 1 Surname",
        "github": "http://github.com/student1",
        "email": "student1@gmail.com"
    }
]